leoneed/__init__.py
leoneed/needle.py
leoneed/stage.py
leoneed/stella.py
leoneed-0.0.3.dist-info/LICENSE
leoneed-0.0.3.dist-info/METADATA
leoneed-0.0.3.dist-info/WHEEL
leoneed-0.0.3.dist-info/top_level.txt
leoneed-0.0.3.dist-info/RECORD
